maskerlogger/__init__.py
maskerlogger/ahocorasick_regex_match.py
maskerlogger/config/gitleaks.toml
maskerlogger/masker_formatter.py
maskerlogger/utils.py
maskerlogger-1.1.0.dist-info/METADATA
maskerlogger-1.1.0.dist-info/WHEEL
maskerlogger-1.1.0.dist-info/licenses/LICENSE
maskerlogger-1.1.0.dist-info/RECORD
