Metadata-Version: 2.4
Name: maskerlogger
Version: 1.1.0
Summary: mask your secrets from your logs
License: MIT
License-File: LICENSE
Author: Tamar Galer
Author-email: tamar@ox.security
Requires-Python: >=3.10
Classifier: Development Status :: 5 - Production/Stable
Classifier: Intended Audience :: Developers
Classifier: License :: OSI Approved :: MIT License
Classifier: Operating System :: OS Independent
Classifier: Programming Language :: Python :: 3
Classifier: Programming Language :: Python :: 3.10
Classifier: Programming Language :: Python :: 3.11
Classifier: Programming Language :: Python :: 3.12
Classifier: Programming Language :: Python :: 3.13
Classifier: Topic :: Software Development :: Libraries :: Python Modules
Classifier: Topic :: System :: Logging
Requires-Dist: pyahocorasick (>=2.1.0,<3.0.0)
Requires-Dist: python-json-logger (>=2.0.7,<4.0.0)
Requires-Dist: tomli (>=2.0.0,<3.0.0)
Project-URL: Source, https://github.com/oxsecurity/MaskerLogger
Project-URL: Tracker, https://github.com/oxsecurity/MaskerLogger/issues
